lib/__init__.py
lib/serverclient.py
serverclient-0.0.2.dist-info/METADATA
serverclient-0.0.2.dist-info/WHEEL
serverclient-0.0.2.dist-info/top_level.txt
serverclient-0.0.2.dist-info/RECORD
